{
  "Actor/AIProgram/GuardianMiniBeam.baiprog": 6765,
  "Actor/AIProgram/RodHeart.baiprog": 12699,
  "Actor/AISchedule/Npc_LynxVTS1.baischedule": 2668,
  "Actor/AS/Npc_Face_EyeClose.bas": 2730,
  "Actor/AS/Npc_LynxVTS1_Face_C_Guard_Wait.bas": 8304,
  "Actor/AS/Npc_LynxVTS1_Face_Default.bas": 12105,
  "Actor/AS/Npc_LynxVTS1_Face_Talk.bas": 9845,
  "Actor/AS/Player_BackJump.bas": 28685,
  "Actor/AS/Player_BackJumpLand.bas": 30780,
  "Actor/AS/Player_CutCharge.bas": 43415,
  "Actor/AS/Player_CutChargeMove.bas": 14240,
  "Actor/AS/Player_CutChargeMoveLower.bas": 44340,
  "Actor/AS/Player_CutChargeWait.bas": 39950,
  "Actor/AS/Player_CutS1.bas": 32170,
  "Actor/AS/Player_CutS2.bas": 24140,
  "Actor/AS/Player_CutS3.bas": 24165,
  "Actor/AS/Player_CutSF.bas": 35520,
  "Actor/AS/Player_DamageL.bas": 27010,
  "Actor/AS/Player_DamageM.bas": 28860,
  "Actor/AS/Player_DamageS.bas": 37525,
  "Actor/AS/Player_DamageSUpper.bas": 23130,
  "Actor/AS/Player_DamageShock.bas": 15985,
  "Actor/AS/Player_Dead.bas": 125221,
  "Actor/AS/Player_DemoWaitAttention.bas": 44010,
  "Actor/AS/Player_FrontRoll.bas": 232857,
  "Actor/AS/Player_HorseRun_Gear4.bas": 125496,
  "Actor/AS/Player_JumpStagger.bas": 126589,
  "Actor/AS/Player_JumpWaitHorseRide.bas": 57925,
  "Actor/AS/Player_LandDamage.bas": 124483,
  "Actor/AS/Player_LandDamageStand.bas": 127998,
  "Actor/AS/Player_LookAroundAttention.bas": 139230,
  "Actor/AS/Player_MoveAttention.bas": 174613,
  "Actor/AS/Player_MoveAttentionUpper.bas": 88051,
  "Actor/AS/Player_MoveUpper.bas": 160483,
  "Actor/AS/Player_Slide.bas": 135220,
  "Actor/AS/Player_SlideBrake.bas": 135441,
  "Actor/AS/Player_SlideLand.bas": 133038,
  "Actor/AS/Player_SquatDamage.bas": 124704,
  "Actor/AS/Player_SquatMoveUpper.bas": 134190,
  "Actor/AS/Player_SquatWaitUpper.bas": 123354,
  "Actor/AS/Player_Step.bas": 30495,
  "Actor/AS/Player_StepLand.bas": 34175,
  "Actor/AS/Player_WaitAttention.bas": 14835,
  "Actor/AS/Player_WaitAttentionUpper.bas": 24320,
  "Actor/AS/Player_WaitDamage.bas": 21230,
  "Actor/AS/Player_WaitUnsteady.bas": 33735,
  "Actor/AS/Player_WaitUpper.bas": 255919,
  "Actor/AS/Player_WeaponThrow.bas": 59820,
  "Actor/AS/Player_WeaponThrowCharge.bas": 23835,
  "Actor/AS/Weapon_Wand_Heart_On.bas": 2425,
  "Actor/AS/Weapon_Wand_Heart_WeaponEquipOn.bas": 2425,
  "Actor/ASList/Item_Glitter_Ore.baslist": 1776,
  "Actor/ASList/Npc_LynxVTS1.baslist": 18977,
  "Actor/ASList/Player.baslist": 119378,
  "Actor/ActorLink/Armor_VTS1_Head.bxml": 2416,
  "Actor/ActorLink/Armor_VTS1_Lower.bxml": 2434,
  "Actor/ActorLink/Armor_VTS1_Upper.bxml": 2434,
  "Actor/ActorLink/HeartBeam.bxml": 2416,
  "Actor/ActorLink/Npc_LynxVTS1.bxml": 2245,
  "Actor/ActorLink/Weapon_Wand_Heart.bxml": 2719,
  "Actor/AnimationInfo/Npc_LynxVTS1.baniminfo": 74832,
  "Actor/GeneralParamList/Armor_VTS1_Head.bgparamlist": 2555,
  "Actor/GeneralParamList/Armor_VTS1_Lower.bgparamlist": 2648,
  "Actor/GeneralParamList/Armor_VTS1_Upper.bgparamlist": 2996,
  "Actor/GeneralParamList/PlayerCryoBeam.bgparamlist": 2390,
  "Actor/GeneralParamList/Weapon_Wand_Heart.bgparamlist": 9900,
  "Actor/Pack/Armor_VTS1_Head.bactorpack": 66112,
  "Actor/Pack/Armor_VTS1_Lower.bactorpack": 4352,
  "Actor/Pack/Armor_VTS1_Upper.bactorpack": 54944,
  "Actor/Pack/GameROMPlayer.bactorpack": 3105184,
  "Actor/Pack/HeartBeam.bactorpack": 5504,
  "Actor/Pack/Npc_LynxVTS1.bactorpack": 294560,
  "Actor/Pack/Weapon_Wand_Heart.bactorpack": 13568,
  "Actor/Physics/Armor_VTS1_Head.bphysics": 5622,
  "Actor/Physics/Armor_VTS1_Lower.bphysics": 3222,
  "Actor/Physics/Armor_VTS1_Upper.bphysics": 4566,
  "Actor/Physics/HeartBeam.bphysics": 9160,
  "Actor/Physics/Npc_LynxVTS1.bphysics": 12232,
  "Actor/ShopData/Npc_LynxVTS1.bshop": 2100,
  "Actor/UMii/Npc_LynxVTS1.bumii": 1768,
  "Aoc/0010/Map/MainField/H-8/H-8_Static.mubin": 175076,
  "Event/EventInfo.product.byml": 620100,
  "Event/Npc_LynxVTS1.beventpack": 156672,
  "EventFlow/Npc_LynxVTS1.bfevfl": 9856,
  "Message/Msg_EUen.product.sarc": 6486436,
  "Message/Msg_USen.product.sarc": 6486436,
  "Model/Armor_VTS1.Tex1.bfres": 6400574,
  "Model/Armor_VTS1.Tex2.bfres": 2284336,
  "Model/Armor_VTS1.bfres": 6106150,
  "Model/Npc_LynxVTS1.Tex1.bfres": 4645534,
  "Model/Npc_LynxVTS1.Tex2.bfres": 1711934,
  "Model/Npc_LynxVTS1.bfres": 3936670,
  "Model/SecondWind_Animation.bfres": 7946000,
  "Model/Weapon_Wand_Heart.Tex1.bfres": 5110949,
  "Model/Weapon_Wand_Heart.Tex2.bfres": 1817528,
  "Model/Weapon_Wand_Heart.bfres": 471384,
  "UI/StockItem/Armor_VTS1_Head.bitemico": 94644,
  "UI/StockItem/Armor_VTS1_Lower.bitemico": 94644,
  "UI/StockItem/Armor_VTS1_Upper.bitemico": 94644,
  "UI/StockItem/Weapon_Wand_Heart.bitemico": 39348
}